django_enum/__init__.py
django_enum/apps.py
django_enum/fields.py
django_enum/operations.py
django_enum/patches.py
django_more/__init__.py
django_more/apps.py
django_more/expressions.py
django_more/hashing.py
django_more/indexes.py
django_more/fields/__init__.py
django_more/fields/hashfield.py
django_more/fields/mixins.py
django_more/fields/nullcharfield.py
django_more/fields/orderbyfield.py
django_more/storages/__init__.py
django_more-0.2.6.dist-info/DESCRIPTION.rst
django_more-0.2.6.dist-info/METADATA
django_more-0.2.6.dist-info/RECORD
django_more-0.2.6.dist-info/WHEEL
django_more-0.2.6.dist-info/metadata.json
django_more-0.2.6.dist-info/top_level.txt
django_types/__init__.py
django_types/fields.py
django_types/operations.py
django_types/patches.py
django_types/utils.py
patchy/__init__.py
patchy/core.py
patchy/testmod.py
patchy/tests.py
