Metadata-Version: 2.0
Name: django-more
Version: 0.2.6
Summary: Django with more
Home-page: https://github.com/ashleywaite/django-more
Author: Ashley Waite
Author-email: ashley.c.waite@gmail.com
License: BSD
Platform: UNKNOWN
Classifier: Development Status :: 4 - Beta
Classifier: Framework :: Django :: 1.11
Classifier: Intended Audience :: Developers
Classifier: License :: OSI Approved :: BSD License
Classifier: Programming Language :: Python :: 3
Classifier: Programming Language :: Python :: 3.5
Classifier: Programming Language :: Python :: 3.6
Requires-Python: >=3.4
Requires-Dist: django
Provides-Extra: test
Requires-Dist: psycopg2; extra == 'test'
Requires-Dist: mysqlclient; extra == 'test'
